researchpal/__init__.py
researchpal/literature_review.py
researchpal-1.0.1.dist-info/LICENSE
researchpal-1.0.1.dist-info/METADATA
researchpal-1.0.1.dist-info/WHEEL
researchpal-1.0.1.dist-info/top_level.txt
researchpal-1.0.1.dist-info/RECORD
