Metadata-Version: 2.1
Name: researchpal
Version: 1.0.1
Summary: Python library for generating literature review
Home-page: UNKNOWN
Author: Veracious.ai
Author-email: info@researchpal.co
License: MIT
Keywords: researchpal,literature review,generate literature review,python literature
Platform: UNKNOWN
Classifier: Development Status :: 5 - Production/Stable
Classifier: License :: OSI Approved :: MIT License
Classifier: Intended Audience :: Developers
Classifier: Intended Audience :: Science/Research
Classifier: Programming Language :: Python :: 3.8
Classifier: Operating System :: MacOS :: MacOS X
Classifier: Operating System :: Unix
Classifier: Operating System :: Microsoft :: Windows
